devopsarr/__init__.py
devopsarr/adapter.py
devopsarr/exceptions.py
devopsarr/models.py
devopsarr/base_services/__init__.py
devopsarr/base_services/tag.py
basearr_py-0.0.2.dist-info/LICENSE
basearr_py-0.0.2.dist-info/METADATA
basearr_py-0.0.2.dist-info/WHEEL
basearr_py-0.0.2.dist-info/top_level.txt
basearr_py-0.0.2.dist-info/RECORD
