Metadata-Version: 2.1
Name: basearr-py
Version: 0.0.2
Summary: Basic API wrapper and utility for the arr world
Project-URL: Homepage, https://github.com/devopsarr/arr-py
Project-URL: Bug Tracker, https://github.com/devopsarr/arr-py/issues
Classifier: Programming Language :: Python :: 3
Classifier: License :: OSI Approved :: Mozilla Public License 2.0 (MPL 2.0)
Classifier: Operating System :: OS Independent
Requires-Python: >=3.7
License-File: LICENSE
Requires-Dist: requests (>=2.28.1)
Requires-Dist: pydantic (>=1.10.2)
